aftermark/__init__.py
aftermark/cli/__init__.py
aftermark/cli/nuke.py
aftermark/utils/__init__.py
aftermark/utils/path.py
aftermark-0.1.1.dist-info/METADATA
aftermark-0.1.1.dist-info/WHEEL
aftermark-0.1.1.dist-info/entry_points.txt
aftermark-0.1.1.dist-info/top_level.txt
aftermark-0.1.1.dist-info/RECORD
