Metadata-Version: 2.4
Name: aftermark
Version: 0.1.1
Requires-Python: >=3.9
Requires-Dist: numpy
Requires-Dist: pillow
Provides-Extra: dev
Requires-Dist: matplotlib; extra == "dev"
Requires-Dist: opencv-python; extra == "dev"
